MANIFEST.in
requirements-dev.txt
requirements.txt
setup.py
jsc/__init__.py
jsc/client.py
jsc/container.py
jsc/logger.py
jsc/recipe.py
jsc/rparser.py
jsc/server.py
jsc/server_updater.py
jsc/sshjsonrpc.py
jsc/sshjsonrpcposix.py
jsc/sshjsonrpcwin.py
jsc/sshrpcutil.py
jsc.egg-info/PKG-INFO
jsc.egg-info/SOURCES.txt
jsc.egg-info/dependency_links.txt
jsc.egg-info/entry_points.txt
jsc.egg-info/pbr.json
jsc.egg-info/requires.txt
jsc.egg-info/top_level.txt
jsc.egg-info/zip-safe
jsc/tests/__init__.py
jsc/tests/fake_sync_endpoint.py
jsc/tests/test_travis.py