Metadata-Version: 1.0
Name: jsc
Version: 6.3
Summary: Jumpstarter Console
Home-page: https://github.com/jumpstarter-io/jsc
Author: Jumpstarter
Author-email: team@jumpstarter.io
License: MIT
Keywords: jumpstarter js jsc deploy
Platform: UNKNOWN
